tests
sphinxtrap
