Metadata-Version: 1.1
Name: sphinxtrap
Version: 0.2.3
Summary: Yet another bootstrap sphinx theme.
Home-page: https://github.com/jfardello/Sphinxtrap
Author: José Manuel Fardello
Author-email: jmfardello@gmail.com
License: MIT
Download-URL: http://pypi.python.org/pypi/sphinxtrap
Keywords: sphinx extension theme
Platform: UNKNOWN
Classifier: Development Status :: 5 - Production/Stable
Classifier: Intended Audience :: Developers
Classifier: License :: OSI Approved :: MIT License
Classifier: Operating System :: OS Independent
Classifier: Programming Language :: Python
Classifier: Programming Language :: Python :: 2
Classifier: Programming Language :: Python :: 3
Classifier: Topic :: Documentation
Classifier: Topic :: Software Development :: Documentation
